MANIFEST.in
README.rst
setup.py
docs/HISTORY.txt
docs/LICENSE.GPL
docs/LICENSE.txt
simplelayout/__init__.py
simplelayout.types.common.egg-info/PKG-INFO
simplelayout.types.common.egg-info/SOURCES.txt
simplelayout.types.common.egg-info/dependency_links.txt
simplelayout.types.common.egg-info/entry_points.txt
simplelayout.types.common.egg-info/namespace_packages.txt
simplelayout.types.common.egg-info/not-zip-safe
simplelayout.types.common.egg-info/requires.txt
simplelayout.types.common.egg-info/top_level.txt
simplelayout/types/__init__.py
simplelayout/types/common/__init__.py
simplelayout/types/common/config.py
simplelayout/types/common/configure.zcml
simplelayout/types/common/interfaces.py
simplelayout/types/common/lawgiver.zcml
simplelayout/types/common/testing.py
simplelayout/types/common/validation.py
simplelayout/types/common/Extensions/__init__.py
simplelayout/types/common/Extensions/install.py
simplelayout/types/common/browser/__init__.py
simplelayout/types/common/browser/configure.zcml
simplelayout/types/common/browser/file.pt
simplelayout/types/common/browser/image.pt
simplelayout/types/common/browser/link.pt
simplelayout/types/common/browser/paragraph.pt
simplelayout/types/common/browser/paragraph_version_view.pt
simplelayout/types/common/browser/views.py
simplelayout/types/common/browser/resources/page_icon.gif
simplelayout/types/common/browser/resources/paragraph_icon.gif
simplelayout/types/common/content/__init__.py
simplelayout/types/common/content/configure.zcml
simplelayout/types/common/content/page.py
simplelayout/types/common/content/paragraph.py
simplelayout/types/common/content/simplelayout_schemas.py
simplelayout/types/common/extender/__init__.py
simplelayout/types/common/extender/configure.zcml
simplelayout/types/common/extender/extend.py
simplelayout/types/common/extender/fields.py
simplelayout/types/common/i18n/simplelayout.types.common-de.po
simplelayout/types/common/i18n/simplelayout.types.common-plone-de.po
simplelayout/types/common/i18n/simplelayout.types.common.pot
simplelayout/types/common/profiles/default/catalog.xml
simplelayout/types/common/profiles/default/diff_tool.xml
simplelayout/types/common/profiles/default/factorytool.xml
simplelayout/types/common/profiles/default/metadata.xml
simplelayout/types/common/profiles/default/repositorytool.xml
simplelayout/types/common/profiles/default/rolemap.xml
