Metadata-Version: 1.0
Name: simplelayout.types.common
Version: 3.1.0
Summary: Simplelayout component providing content types.
Home-page: https://github.com/4teamwork/simplelayout.types.common
Author: 4teamwork GmbH
Author-email: mailto:info@4teamwork.ch
License: GPL2
Platform: UNKNOWN
Classifier: Framework :: Plone
Classifier: Programming Language :: Python
Classifier: Topic :: Software Development :: Libraries :: Python Modules
